{
  "user": [
    {
      "id": "2da2",
      "title": "Вторая новость",
      "news": "вторая новость должна быть намного длиннее, что бы можно быдо посмотреть как она отображается на странице и видеть возможные недостатки в верстке и в написании.  Надеюсь что такая длина записи хватит для понимания всего того что мне нужно увидеть",
      "author": "Алиев Ораз редактор"
    },
    {
      "id": "2dbb",
      "title": "Новость 3",
      "news": "Создание новости для заполнения контента и поверки работоспособности разных участков кода.\nДальше продолжать заполнять контент могут разные пользователи с указание своего авторства. Не использовал ТайпСкрипт, потому что тест задание не подразумевало данную технологию\n",
      "author": "Ораз Алиев"
    }
  ]
}